{
  "timestamp": "2026-07-24T17:59:22.614219+08:00",
  "type": "evening",
  "price": {
    "price_usd": 0.069995,
    "price_btc": 1.08e-06,
    "change_24h_pct": -3.13334,
    "change_7d_pct": -2.00534,
    "change_30d_pct": -11.49144,
    "market_cap_usd": 10863190348,
    "volume_24h_usd": 840961354,
    "market_cap_rank": 11,
    "ath_usd": 0.731578,
    "ath_date": "2021-05-07T21:08:23.000Z",
    "atl_usd": 8.69e-05,
    "atl_date": "2015-05-05T16:00:00.000Z",
    "high_24h_usd": 0.072472,
    "low_24h_usd": 0.068709,
    "circulating_supply": 155201346383.7052,
    "total_supply": 170913053126.579,
    "max_supply": null
  },
  "chain": {
    "blocks": 6444928,
    "transactions_24h": 30738,
    "circulation": 1.7091336312657908e+19,
    "difficulty": 47373928.75689308,
    "hashrate_24h": "3229674149889820",
    "mempool_transactions": 54,
    "mempool_size": 14419,
    "mempool_tps": 0.26666666666666666,
    "mempool_total_fee_usd": 0.6071,
    "average_transaction_fee_24h_usd": null,
    "median_transaction_fee_24h_usd": null,
    "fee_24h_usd": null,
    "largest_transaction_24h_usd": 38574724,
    "nodes": 503,
    "outputs_24h": null,
    "cdd_24h": 16024187280.306757,
    "hodling_addresses": 8400679,
    "suggested_fee_per_byte_sat": 500000
  },
  "whale": {
    "status": "ok",
    "activity_level": "有动静",
    "activity_score": 23,
    "summary": "最大单笔$38,574,724",
    "largest_tx_24h_usd": 38574724,
    "fee_total_24h_usd": 0,
    "vol_mcap_ratio_pct": 7.7,
    "mempool_count": 54,
    "tx_count_24h": 30738,
    "cdd_24h": 16024187280.306757,
    "hodling_addresses": 8400679,
    "suggested_fee_per_byte": 500000
  },
  "analysis": {
    "summary": "短线走弱，观望为主；巨鲸：有动静，最大单笔$38,574,724",
    "phase": "窄幅整理，等待方向选择",
    "support": 0.0651,
    "resistance": 0.07489,
    "major_support": 0.0616,
    "major_resistance": 0.07839,
    "key_indicators": {
      "vol_mcap_ratio": 7.7,
      "transactions_24h": 30738,
      "hashrate_24h": "3229674149889820",
      "mempool_txs": 54
    }
  }
}