{
  "timestamp": "2026-07-09T20:19:00.061761+08:00",
  "type": "evening",
  "price": {
    "price_usd": 0.072327,
    "price_btc": 1.15e-06,
    "change_24h_pct": 0.364,
    "change_7d_pct": -2.10932,
    "change_30d_pct": -15.32677,
    "market_cap_usd": 11211813780,
    "volume_24h_usd": 418083286,
    "market_cap_rank": 11,
    "ath_usd": 0.731578,
    "ath_date": "2021-05-08T05:08:23.458Z",
    "atl_usd": 8.69e-05,
    "atl_date": "2015-05-06T00:00:00.000Z",
    "high_24h_usd": 0.072948,
    "low_24h_usd": 0.071374,
    "circulating_supply": 154998026383.7052,
    "total_supply": 154998026383.7052,
    "max_supply": null
  },
  "chain": {
    "blocks": 6424617,
    "transactions_24h": 26855,
    "circulation": 1.7071025312657908e+19,
    "difficulty": 44007484.35669757,
    "hashrate_24h": "3000169913638781",
    "mempool_transactions": 62,
    "mempool_size": 41342,
    "mempool_tps": 0,
    "mempool_total_fee_usd": 2.4424,
    "average_transaction_fee_24h_usd": null,
    "median_transaction_fee_24h_usd": null,
    "fee_24h_usd": null,
    "largest_transaction_24h_usd": 40959284,
    "nodes": 518,
    "outputs_24h": null,
    "cdd_24h": 58453861482.63606,
    "hodling_addresses": 8384191,
    "suggested_fee_per_byte_sat": 500000
  },
  "whale": {
    "status": "ok",
    "activity_level": "有动静",
    "activity_score": 23,
    "summary": "⚠️ CDD偏高(58.5B)，老币在流动；最大单笔$40,959,284",
    "largest_tx_24h_usd": 40959284,
    "fee_total_24h_usd": 0,
    "vol_mcap_ratio_pct": 3.7,
    "mempool_count": 62,
    "tx_count_24h": 26855,
    "cdd_24h": 58453861482.63606,
    "hodling_addresses": 8384191,
    "suggested_fee_per_byte": 500000
  },
  "analysis": {
    "summary": "短线横盘震荡；巨鲸：有动静，⚠️ CDD偏高(58.5B)，老币在流动；最大单笔$40,959,284",
    "phase": "窄幅整理，等待方向选择",
    "support": 0.06726,
    "resistance": 0.07739,
    "major_support": 0.06365,
    "major_resistance": 0.08101,
    "key_indicators": {
      "vol_mcap_ratio": 3.7,
      "transactions_24h": 26855,
      "hashrate_24h": "3000169913638781",
      "mempool_txs": 62
    }
  }
}